wikipya/__init__.py
wikipya/aiowiki.py
wikipya/clients.py
wikipya/constants.py
wikipya/exceptions.py
wikipya/methods/__init__.py
wikipya/methods/fa_facade_search.py
wikipya/methods/fd_search.py
wikipya/methods/fetch_all.py
wikipya/methods/get_page_name.py
wikipya/methods/image.py
wikipya/methods/lib.py
wikipya/methods/opensearch.py
wikipya/methods/page.py
wikipya/methods/search.py
wikipya/methods/search_with_description.py
wikipya/methods/sections.py
wikipya/methods/summary.py
wikipya/models/__init__.py
wikipya/models/image.py
wikipya/models/opensearch.py
wikipya/models/page.py
wikipya/models/search.py
wikipya/models/section.py
wikipya/models/suggestion.py
wikipya/models/summary.py
wikipya/models/tghtml.py
wikipya/models/url.py
wikipya-4.1.0.dist-info/LICENSE
wikipya-4.1.0.dist-info/METADATA
wikipya-4.1.0.dist-info/WHEEL
wikipya-4.1.0.dist-info/RECORD
