Metadata-Version: 2.1
Name: wikipya
Version: 4.1.0
Summary: A simple async python library for search pages and images in wikis
Home-page: https://github.com/jDan735/wikipya
License: MIT
Keywords: api,wikipedia,mediawiki,asyncio
Author: Daniel Zakharov
Author-email: gzdan734@gmail.com
Requires-Python: >=3.10,<4.0
Classifier: License :: OSI Approved :: MIT License
Classifier: Programming Language :: Python :: 3
Classifier: Programming Language :: Python :: 3.10
Classifier: Programming Language :: Python :: 3.11
Classifier: Programming Language :: Python :: 3.12
Requires-Dist: beautifulsoup4 (>=4.10.0,<5.0.0)
Requires-Dist: httpx (>=0.27.2,<0.28.0)
Requires-Dist: pydantic (>=2.5.3,<2.9.0)
Requires-Dist: tghtml (>=1.2.0,<2.0.0)
Project-URL: Repository, https://github.com/jDan735/wikipya
